nonebot_plugin_justsix/__init__.py
nonebot_plugin_justsix/example.py
nonebot_plugin_justsix-1.0.0.dist-info/LICENSE
nonebot_plugin_justsix-1.0.0.dist-info/METADATA
nonebot_plugin_justsix-1.0.0.dist-info/WHEEL
nonebot_plugin_justsix-1.0.0.dist-info/RECORD
