Metadata-Version: 2.1
Name: nonebot-plugin-justsix
Version: 1.0.0
Summary: 一个nonebot2的发6插件
Home-page: https://github.com/iidamie/nonebot_plugin_justsix
Author: Maximilian Wu
Author-email: me@maxng.cc
Requires-Python: >=3.9,<4.0
Classifier: Programming Language :: Python :: 3
Classifier: Programming Language :: Python :: 3.9
Classifier: Programming Language :: Python :: 3.10
Classifier: Programming Language :: Python :: 3.11
Requires-Dist: build (>=0.1.0,<0.2.0)
Requires-Dist: httpx (>=0.21.3,<0.22.0)
Requires-Dist: nonebot-adapter-onebot (>=2.0.0-beta.1,<3.0.0)
Requires-Dist: nonebot2 (>=2.0.0-beta.1,<3.0.0)
Requires-Dist: twine (>=3.3.0,<4.0.0)
Project-URL: Repository, https://github.com/iidamie/nonebot_plugin_justsix
